README.md
setup.cfg
setup.py
src/dawa/__init__.py
src/dawa/models.py
src/dawa/api/__init__.py
src/dawa/api/dawa.py
src/django_dawa.egg-info/PKG-INFO
src/django_dawa.egg-info/SOURCES.txt
src/django_dawa.egg-info/dependency_links.txt
src/django_dawa.egg-info/requires.txt
src/django_dawa.egg-info/top_level.txt